peter_cullen_burbery_python_functions/__init__.py
peter_cullen_burbery_python_functions/date_time_functions/__init__.py
peter_cullen_burbery_python_functions/date_time_functions/date_time_functions.py
peter_cullen_burbery_python_functions/image_functions/__init__.py
peter_cullen_burbery_python_functions/image_functions/image_functions.py
peter_cullen_burbery_python_functions/system_management_functions/__init__.py
peter_cullen_burbery_python_functions/system_management_functions/system_management_functions.py
peter_cullen_burbery_python_functions-1.8.1.dist-info/licenses/LICENSE
peter_cullen_burbery_python_functions-1.8.1.dist-info/METADATA
peter_cullen_burbery_python_functions-1.8.1.dist-info/WHEEL
peter_cullen_burbery_python_functions-1.8.1.dist-info/top_level.txt
peter_cullen_burbery_python_functions-1.8.1.dist-info/RECORD
