Metadata-Version: 2.4
Name: peter_cullen_burbery_python_functions
Version: 1.8.1
Summary: Utility functions by Peter Cullen Burbery, including date_time_stamp, compare_images, convert_blob_to_raw_github_url, validate_Windows_filename_with_reasons, and valid_Windows_filename
Author-email: Peter Cullen Burbery <peter.cullen.burbery@gmail.com>
License-Expression: MIT
Project-URL: Homepage, https://github.com/PeterCullenBurbery/peter-cullen-burbery-python-functions
Project-URL: Documentation, https://peter-cullen-burbery-python-functions.readthedocs.io
Project-URL: Source, https://github.com/PeterCullenBurbery/peter-cullen-burbery-python-functions
Requires-Python: >=3.9
License-File: LICENSE
Requires-Dist: tzlocal
Requires-Dist: Pillow
Requires-Dist: opencv-python
Requires-Dist: scikit-image
Requires-Dist: requests
Requires-Dist: sphinx
Requires-Dist: sphinx_rtd_theme
Dynamic: license-file
